seadex_sonarr/__init__.py
seadex_sonarr/modules/__init__.py
seadex_sonarr/modules/anilist.py
seadex_sonarr/modules/discord.py
seadex_sonarr/modules/log.py
seadex_sonarr/modules/seadex_sonarr.py
seadex_sonarr-0.0.2.dist-info/licenses/LICENSE
seadex_sonarr-0.0.2.dist-info/METADATA
seadex_sonarr-0.0.2.dist-info/WHEEL
seadex_sonarr-0.0.2.dist-info/top_level.txt
seadex_sonarr-0.0.2.dist-info/RECORD
