Metadata-Version: 2.4
Name: seadex_sonarr
Version: 0.0.2
Summary: SeaDex Sonarr Sync
Author: bbtufty
Maintainer: bbtufty
License:                     GNU GENERAL PUBLIC LICENSE
Project-URL: Homepage, https://github.com/bbtufty/seadex-sonarr
Project-URL: Bug Reports, https://github.com/bbtufty/seadex-sonarr/issues
Project-URL: Source, https://github.com/bbtufty/seadex-sonarr
Classifier: Development Status :: 3 - Alpha
Classifier: License :: OSI Approved :: GNU General Public License v3 or later (GPLv3+)
Classifier: Programming Language :: Python
Classifier: Programming Language :: Python :: 3
Classifier: Programming Language :: Python :: 3.11
Classifier: Programming Language :: Python :: 3.12
Classifier: Programming Language :: Python :: 3 :: Only
Requires-Python: >=3.11
License-File: LICENSE
Requires-Dist: arrapi==1.4.13
Requires-Dist: colorlog==6.9.0
Requires-Dist: discordwebhook==1.0.3
Requires-Dist: requests==2.32.4
Requires-Dist: seadex==0.7.1
Provides-Extra: docs
Requires-Dist: sphinx-automodapi==0.20.0; extra == "docs"
Requires-Dist: sphinx-rtd-theme==3.0.2; extra == "docs"
Dynamic: license-file
